seisloc/__init__.py
seisloc/cata.py
seisloc/cluster.py
seisloc/day_split.py
seisloc/dd.py
seisloc/deco.py
seisloc/eqt.py
seisloc/geometry.py
seisloc/geopara.py
seisloc/hypoinv.py
seisloc/math.py
seisloc/noise.py
seisloc/phase_convert.py
seisloc/plot.py
seisloc/real.py
seisloc/sac.py
seisloc/scc.py
seisloc/seis.py
seisloc/spatial.py
seisloc/spectrum.py
seisloc/sta.py
seisloc/statistics.py
seisloc/template_matching.py
seisloc/text_io.py
seisloc/tomo.py
seisloc/utils.py
seisloc/velest.py
seisloc/velocity.py
seisloc/wf/__init__.py
seisloc/wf/evewf.py
seisloc/wf/telewf.py
seisloc-0.1.13.dist-info/LICENSE
seisloc-0.1.13.dist-info/METADATA
seisloc-0.1.13.dist-info/WHEEL
seisloc-0.1.13.dist-info/top_level.txt
seisloc-0.1.13.dist-info/RECORD
