Metadata-Version: 2.1
Name: seisloc
Version: 0.1.13
Summary: Tool package for earthquake location
Author: Hardy ZI
Author-email: zijinping@hotmail.com
License: MIT
Requires-Python: >=3.7
License-File: LICENSE
Requires-Dist: obspy
Requires-Dist: tqdm >=4.48.0
Requires-Dist: jupyter
Requires-Dist: scipy >=1.4.1
Requires-Dist: numpy >=1.21.0
Requires-Dist: numba
Requires-Dist: pandas
Requires-Dist: pillow
